fc_nmap/GrpcClient.py
fc_nmap/__about__.py
fc_nmap/__init__.py
fc_nmap/__main__.py
fc_nmap/dbexports.py
fc_nmap/dbexports_maps.py
fc_nmap/get_hubs.py
fc_nmap/hubs.db
fc_nmap/ip2location.py
fc_nmap/cli/__init__.py
fc_nmap/fcproto/gossip_pb2.py
fc_nmap/fcproto/gossip_pb2.pyi
fc_nmap/fcproto/gossip_pb2_grpc.py
fc_nmap/fcproto/hub_event_pb2.py
fc_nmap/fcproto/hub_event_pb2.pyi
fc_nmap/fcproto/hub_event_pb2_grpc.py
fc_nmap/fcproto/hub_state_pb2.py
fc_nmap/fcproto/hub_state_pb2.pyi
fc_nmap/fcproto/hub_state_pb2_grpc.py
fc_nmap/fcproto/job_pb2.py
fc_nmap/fcproto/job_pb2.pyi
fc_nmap/fcproto/job_pb2_grpc.py
fc_nmap/fcproto/message_pb2.py
fc_nmap/fcproto/message_pb2.pyi
fc_nmap/fcproto/message_pb2_grpc.py
fc_nmap/fcproto/onchain_event_pb2.py
fc_nmap/fcproto/onchain_event_pb2.pyi
fc_nmap/fcproto/onchain_event_pb2_grpc.py
fc_nmap/fcproto/request_response_pb2.py
fc_nmap/fcproto/request_response_pb2.pyi
fc_nmap/fcproto/request_response_pb2_grpc.py
fc_nmap/fcproto/rpc_pb2.py
fc_nmap/fcproto/rpc_pb2.pyi
fc_nmap/fcproto/rpc_pb2_grpc.py
fc_nmap/fcproto/sync_trie_pb2.py
fc_nmap/fcproto/sync_trie_pb2.pyi
fc_nmap/fcproto/sync_trie_pb2_grpc.py
fc_nmap/fcproto/username_proof_pb2.py
fc_nmap/fcproto/username_proof_pb2.pyi
fc_nmap/fcproto/username_proof_pb2_grpc.py
fc_nmap-0.0.10.dist-info/METADATA
fc_nmap-0.0.10.dist-info/WHEEL
fc_nmap-0.0.10.dist-info/entry_points.txt
fc_nmap-0.0.10.dist-info/licenses/LICENSE.txt
fc_nmap-0.0.10.dist-info/RECORD
