Metadata-Version: 2.3
Name: fc-nmap
Version: 0.0.10
Summary: Farcaster network mapping
Project-URL: Documentation, https://github.com/vrypan/fc-nmap#readme
Project-URL: Issues, https://github.com/vrypan/fc-nmap/issues
Project-URL: Source, https://github.com/vrypan/fc-nmap
Author-email: vrypan <vrypan@gmail.comm>
License-Expression: MIT
License-File: LICENSE.txt
Classifier: Development Status :: 4 - Beta
Classifier: Programming Language :: Python
Classifier: Programming Language :: Python :: 3.8
Classifier: Programming Language :: Python :: 3.9
Classifier: Programming Language :: Python :: 3.10
Classifier: Programming Language :: Python :: 3.11
Classifier: Programming Language :: Python :: 3.12
Classifier: Programming Language :: Python :: Implementation :: CPython
Classifier: Programming Language :: Python :: Implementation :: PyPy
Requires-Python: >=3.8
Requires-Dist: click
Requires-Dist: folium
Requires-Dist: grpcio
Requires-Dist: ipaddress
Requires-Dist: protobuf
Requires-Dist: requests
